callback_error_plugin_demo_8/__init__.py
callback_error_plugin_demo_8-0.0.2.dist-info/METADATA
callback_error_plugin_demo_8-0.0.2.dist-info/WHEEL
callback_error_plugin_demo_8-0.0.2.dist-info/entry_points.txt
callback_error_plugin_demo_8-0.0.2.dist-info/top_level.txt
callback_error_plugin_demo_8-0.0.2.dist-info/RECORD
